flowchart_magic/__init__.py
flowchart_magic/flowchart_magic.py
flowchart_magic-0.1.6.dist-info/METADATA
flowchart_magic-0.1.6.dist-info/WHEEL
flowchart_magic-0.1.6.dist-info/top_level.txt
flowchart_magic-0.1.6.dist-info/RECORD
