Metadata-Version: 2.1
Name: flowchart-magic
Version: 0.1.6
Summary: Un magic %%flowchart para generar diagramas de flujo en Google Colab.
Author-email: Manuel Garcés <manugp1994@gmail.com>
License: MIT
Project-URL: Homepage, https://github.com/tuusuario/colab-flowchart
Project-URL: Bug Tracker, https://github.com/tuusuario/colab-flowchart/issues
Keywords: google colab,flowchart,magic command,python
Requires-Python: >=3.7
Requires-Dist: pyflowchart>=0.3.1
Requires-Dist: IPython>=7.0.0
